paggcerto/__init__.py
paggcerto/client.py
paggcerto/types.py
paggcerto/utils/__init__.py
paggcerto/utils/make_enum_json_serializable.py
paggcerto_python-0.0.3.dist-info/METADATA
paggcerto_python-0.0.3.dist-info/RECORD
paggcerto_python-0.0.3.dist-info/WHEEL
paggcerto_python-0.0.3.dist-info/top_level.txt
