Metadata-Version: 2.1
Name: paggcerto-python
Version: 0.0.3
Summary: Python bindings for Paggcerto API
Home-page: https://github.com/tassio/paggcerto-python
Author: Tássio Guimarães
Author-email: tassio.acg@gmail.com
License: Apache License
Project-URL: Bug Reports, https://github.com/tassio/paggcerto-python/issues
Keywords: paggcerto api rest payment
Platform: UNKNOWN
Classifier: Development Status :: 3 - Alpha
Classifier: Intended Audience :: Developers
Classifier: Topic :: Software Development :: Build Tools
Classifier: License :: OSI Approved :: Apache Software License
Classifier: Programming Language :: Python :: 2
Classifier: Programming Language :: Python :: 2.7
Classifier: Programming Language :: Python :: 3
Classifier: Programming Language :: Python :: 3.4
Classifier: Programming Language :: Python :: 3.5
Classifier: Programming Language :: Python :: 3.6
Classifier: Programming Language :: Python :: 3.7
Classifier: Topic :: Software Development :: Libraries :: Python Modules
Provides-Extra: dev
Provides-Extra: test
Requires-Dist: python-http-client
Requires-Dist: dataclasses
Provides-Extra: dev
Requires-Dist: check-manifest; extra == 'dev'
Provides-Extra: test
Requires-Dist: coverage; extra == 'test'
